cowbase/__init__.py
cowbase/cowbase_m1.py
cowbase/cowbase_m2.py
cowbase/cowbase_m3.py
cowbase/cowbase_m4.py
cowbase/cowbase_m5.py
cowbase/utils/M1_restoreDB.sql
cowbase/utils/M1_tableDict.json
cowbase/utils/M2_tableDict.json
cowbase/utils/M3_tableDict.json
cowbase/utils/M4_sqlupdate.json
cowbase/utils/M4_tableDict.json
cowbase/utils/config.toml
cowbase/utils/config_farm.toml
cowbase/utils/serverSettings.json
cowbase-1.0.5.dist-info/licenses/LICENSE
cowbase-1.0.5.dist-info/METADATA
cowbase-1.0.5.dist-info/WHEEL
cowbase-1.0.5.dist-info/top_level.txt
cowbase-1.0.5.dist-info/RECORD
