Metadata-Version: 2.4
Name: cowbase
Version: 1.0.5
Summary: A Library for Dairy Farm Data Handling and Curation in Python
Author-email: Martin Julius Gote <martin.gote@kuleuven.be>
License-Expression: MIT
Project-URL: Homepage, https://gitlab.kuleuven.be/livestock-technology/cowbase
Classifier: Development Status :: 5 - Production/Stable
Classifier: Intended Audience :: Science/Research
Classifier: Operating System :: POSIX :: Linux
Classifier: Operating System :: Microsoft :: Windows :: Windows 10
Classifier: Programming Language :: Python :: 3
Requires-Python: >=3.10
License-File: LICENSE
Requires-Dist: DateTime>=5.3
Requires-Dist: numpy>=1.26.0
Requires-Dist: pandas>=2.1.0
Requires-Dist: pathlib>=1.0
Requires-Dist: tomli>=2.0.0
Requires-Dist: sqlalchemy>=2.0.0
Requires-Dist: paramiko>=3.3.0
Requires-Dist: scipy>=1.11.1
Requires-Dist: statsmodels>=0.14.0
Requires-Dist: scikit-learn>=1.3.0
Requires-Dist: tqdm>=4.66.0
Requires-Dist: seaborn>=0.13.0
Requires-Dist: matplotlib>=3.7.0
Requires-Dist: meteostat>=1.6.7
Requires-Dist: sqlalchemy-utils>=0.41.0
Requires-Dist: pymysql>=1.0.3
Requires-Dist: psycopg>=3.1
Requires-Dist: psycopg_binary>=3.1
Dynamic: license-file
